dagoptimizer/__init__.py
dagoptimizer/dag_class.py
dagoptimizer-1.0.1.dist-info/licenses/LICENSE
dagoptimizer-1.0.1.dist-info/METADATA
dagoptimizer-1.0.1.dist-info/WHEEL
dagoptimizer-1.0.1.dist-info/entry_points.txt
dagoptimizer-1.0.1.dist-info/top_level.txt
dagoptimizer-1.0.1.dist-info/RECORD
