Metadata-Version: 2.4
Name: dagoptimizer
Version: 1.0.1
Summary: Advanced DAG optimization library with adaptive transitive reduction, PERT/CPM analysis, and 25+ research-grade metrics
Home-page: https://github.com/SahilShrivastava-Dev/Optimisation_of_DAGs
Author: Sahil Shrivastava
Author-email: Sahil Shrivastava <sahilshrivastava28@gmail.com>
Maintainer-email: Sahil Shrivastava <sahilshrivastava28@gmail.com>
License: MIT
Project-URL: Homepage, https://github.com/SahilShrivastava-Dev/Optimisation_of_DAGs
Project-URL: Documentation, https://github.com/SahilShrivastava-Dev/Optimisation_of_DAGs/wiki
Project-URL: Repository, https://github.com/SahilShrivastava-Dev/Optimisation_of_DAGs
Project-URL: Bug Tracker, https://github.com/SahilShrivastava-Dev/Optimisation_of_DAGs/issues
Project-URL: Demo Application, https://github.com/SahilShrivastava-Dev/Optimisation_of_DAGs#demo-application
Keywords: dag,graph,optimization,transitive-reduction,pert,cpm,critical-path,networkx,directed-acyclic-graph,graph-algorithms,workflow-optimization
Classifier: Development Status :: 5 - Production/Stable
Classifier: Intended Audience :: Developers
Classifier: Intended Audience :: Science/Research
Classifier: Topic :: Software Development :: Libraries :: Python Modules
Classifier: Topic :: Scientific/Engineering :: Mathematics
Classifier: License :: OSI Approved :: MIT License
Classifier: Programming Language :: Python :: 3
Classifier: Programming Language :: Python :: 3.8
Classifier: Programming Language :: Python :: 3.9
Classifier: Programming Language :: Python :: 3.10
Classifier: Programming Language :: Python :: 3.11
Classifier: Programming Language :: Python :: 3.12
Requires-Python: >=3.8
License-File: LICENSE
Requires-Dist: networkx>=2.6
Requires-Dist: numpy>=1.20
Requires-Dist: scipy>=1.7
Provides-Extra: dev
Requires-Dist: pytest>=7.0.0; extra == "dev"
Requires-Dist: pytest-cov>=4.0.0; extra == "dev"
Requires-Dist: black>=22.0.0; extra == "dev"
Requires-Dist: flake8>=5.0.0; extra == "dev"
Requires-Dist: mypy>=0.990; extra == "dev"
Provides-Extra: neo4j
Requires-Dist: neo4j>=5.0.0; extra == "neo4j"
Provides-Extra: visualization
Requires-Dist: matplotlib>=3.5.0; extra == "visualization"
Requires-Dist: pygraphviz>=1.10; extra == "visualization"
Provides-Extra: ai
Requires-Dist: openai>=1.0.0; extra == "ai"
Requires-Dist: anthropic>=0.5.0; extra == "ai"
Provides-Extra: all
Requires-Dist: dagoptimizer[ai,dev,neo4j,visualization]; extra == "all"
Dynamic: author
Dynamic: home-page
Dynamic: license-file
Dynamic: requires-python
